{"galleryinfo": {"HID": 398, "HH": [1, 5], "HN": [1, 398], "HB": "Paulownia tomentosa, (Thunb.) Steud.", "HC": 26, "gallery": [{"IN": "Paulownia - Empress Tree/Empress Tree - Flower Bud.jpg", "IC": [1, 35]}, {"IN": "Paulownia - Empress Tree/Empress Tree - Canopy.jpg", "IC": [1, 6]}, {"IN": "Paulownia - Empress Tree/Empress Tree - Leaf New.jpg", "IC": [1, 85]}, {"IN": "Paulownia - Empress Tree/Empress Tree - Leaf.jpg", "IC": [1, 76]}, {"IN": "Paulownia - Empress Tree/Empress Tree - Bark.jpg", "IC": [1, 1]}, {"IN": "Paulownia - Empress Tree/Empress Tree - Branch.jpg", "IC": [1, 4]}, {"IN": "Paulownia - Empress Tree/Empress Tree - 0000.jpg", "IC": [0, "0000"]}, {"IN": "Paulownia - Empress Tree/Empress Tree - 0001.jpg", "IC": [0, "0001"]}, {"IN": "Paulownia - Empress Tree/Empress Tree - 0002.jpg", "IC": [0, "0002"]}, {"IN": "Paulownia - Empress Tree/Empress Tree - 0003.jpg", "IC": [0, "0003"]}, {"IN": "Paulownia - Empress Tree/Empress Tree - 0004.jpg", "IC": [0, "0004"]}, {"IN": "Paulownia - Empress Tree/Empress Tree - 0005.jpg", "IC": [0, "0005"]}, {"IN": "Paulownia - Empress Tree/Empress Tree - 0006.jpg", "IC": [0, "0006"]}, {"IN": "Paulownia - Empress Tree/Empress Tree - 0007.jpg", "IC": [0, "0007"]}, {"IN": "Paulownia - Empress Tree/Empress Tree - 0008.jpg", "IC": [0, "0008"]}, {"IN": "Paulownia - Empress Tree/Empress Tree - 0009.jpg", "IC": [0, "0009"]}, {"IN": "Paulownia - Empress Tree/Empress Tree - 0010.jpg", "IC": [0, "0010"]}, {"IN": "Paulownia - Empress Tree/Empress Tree - 0011.jpg", "IC": [0, "0011"]}, {"IN": "Paulownia - Empress Tree/Empress Tree - 0012.jpg", "IC": [0, "0012"]}, {"IN": "Paulownia - Empress Tree/Empress Tree - 0013.jpg", "IC": [0, "0013"]}, {"IN": "Paulownia - Empress Tree/Empress Tree - 0014.jpg", "IC": [0, "0014"]}, {"IN": "Paulownia - Empress Tree/Empress Tree - 0015.jpg", "IC": [0, "0015"]}, {"IN": "Paulownia - Empress Tree/Empress Tree - 0016.jpg", "IC": [0, "0016"]}, {"IN": "Paulownia - Empress Tree/Empress Tree - 0017.jpg", "IC": [0, "0017"]}, {"IN": "Paulownia - Empress Tree/Empress Tree - 0018.jpg", "IC": [0, "0018"]}, {"IN": "Paulownia - Empress Tree/Empress Tree - 0019.jpg", "IC": [0, "0019"]}]}, "cardinfo": [{"CN": 6, "CV": [{"N": 19, "V": [1, 5, 398]}, {"N": 32, "V": [1, 3, 0]}, {"N": 7, "V": [0, "", "Scrophulariaceae"]}, {"N": 8, "V": [0, "", "Paulownia"]}, {"N": 26, "V": [0, "", "tomentosa"]}, {"N": 2, "V": [0, "", "(Thunb.) Steud."]}, {"N": 4, "V": [0, "", "dog flower"]}, {"N": 25, "V": [1, 2, 0]}, {"N": 10, "V": [0, "", "10-25m"]}, {"N": 9, "V": [1, 1, 0]}], "CI": "Paulownia - Empress Tree/Empress Tree - Canopy.jpg"}, {"CN": 9, "CV": [{"N": 17, "V": [0, "", "<a href=\"http://www.flowersofindia.net/catalog/slides/Empress%20Tree.html\" target=\"_blank\">flowersofindia</a><br /><a href=\"http://www.ars-grin.gov/cgi-bin/npgs/html/taxon.pl?27045\" target=\"_blank\">ars-grin</a><br /><a href=\"http://www.theplantlist.org/tpl/record/kew-2542391\" target=\"_blank\">theplantlist</a>"]}, {"N": 6, "V": [0, "", "Empress Tree is a deciduous tree native to central and western China. It grows to 10-25 m tall, with large heart-shaped to five-lobed leaves 15-40 cm across, arranged in opposite pairs on the stem. On young growth, the leaves may be in whorls of three and be much bigger than the leaves on more mature growth. The flowers are produced before the leaves in early spring, on panicles 10-30 cm long, with a tubular purple corolla 4-6 cm long resembling a foxglove flower. The fruit is a dry egg-shaped capsule 3-4 cm long, containing numerous tiny seeds. Empress tree is a really fast growing tree. The Chinese plant this tree when their daughter is born. When she marries, they cut the tree down and make furniture and other useful things for her and her new husband. This tree is rare in India."]}, {"N": 20, "V": [0, "", ["China"]]}]}, {"CN": 7, "CV": [{"N": 12, "V": [0, "", "<b>Common</b>: </i>Empress tree, Princess tree, Foxglove tree, Pao tong</i>"]}]}, {"CN": 0, "CV": [{"N": 3, "V": [1, 0, 5]}, {"N": 11, "V": [0, "", "Color: dark grey"]}], "CI": "Paulownia - Empress Tree/Empress Tree - Bark.jpg"}, {"CN": 3, "CV": [{"N": 3, "V": [1, 0, 8]}], "CI": "Paulownia - Empress Tree/Empress Tree - Flower Bud.jpg"}, {"CN": 4, "CV": [{"N": 23, "V": [0, "", "egg like"]}]}, {"CN": 8, "CV": [{"N": 32, "V": [1, 4, 6]}, {"N": 13, "V": [0, "", "5"]}], "CI": "Paulownia - Empress Tree/Empress Tree - Leaf.jpg"}], "mapinfo": [{"lat": "12.94918352", "long": "77.58546388"}], "mapregion": [["12.94918352", "77.58546388"], ["12.94918352", "77.58546388"]]}
