{"Wiki": "http://en.wikipedia.org/wiki/Heliotropium_foertherianum", "Bark Color": "grey", "Common Family": "Forget me not", "Name": "Octopus Bush Tree", "Family": "Boraginaceae", "Leaves Type": "oval", "Flowers Color": "white", "Grow Type": "Evergreen", "Links": ["http://www.flowersofindia.net/catalog/slides/", "http://www.ars-grin.gov/cgi-bin/npgs/html/taxon.pl?464802", "http://www.theplantlist.org/tpl/record/kew-2844023"], "Authority": "Diane & Hilger", "Where": ["Minicoy, Lakshadweep"], "Images": ["Octopus Bush Tree", ["0000", "0001", "0002", "0003", "0004", "0005", "0006", "0007", "0008", "Bark", "Branch", "Canopy", "Flower Bud", "Flower", "Fruit Falling", "Fruit Tender", "Fruit", "Leaf Tender", "Leaf"]], "Size": "Small", "Fruits Color": "green to black", "Description": "Heliotropium foertherianum is a species of flowering plant in the borage family, Boraginaceae. It is native to tropical Asia, including southern China, Madagascar, northern Australia, and most of the atolls and high islands of Micronesia and Polynesia. Common names include Tree Heliotrope, Velvet Soldierbush and Octopus Bush. It is a shrub or small tree typical of littoral zones reaching a height of 6 m (20 ft), with a similar spread.", "Genus": "Heliotropium", "Type": "Tree", "Species": "foertherianum", "Native": ["Asia"]}
