{"galleryinfo": {"HID": 109, "HH": 5, "HN": 109, "HB": "Phyllanthus acidus, (L.) Skeels", "HC": 22, "gallery": "34,71,59,6,76,1,0000,0001,0002,0003,0004,0005,0006,0007,0008,0009,0010,0011,0012,0013,0014,0015"}, "cardinfo": [{"CN": 6, "CV": [{"N": 37, "V": [1, 5, 109]}, {"N": 60, "V": [1, 3, 0]}, {"N": 12, "V": [0, "", "Phyllanthaceae"]}, {"N": 14, "V": [0, "", "Phyllanthus"]}, {"N": 49, "V": [0, "", "Acidus"]}, {"N": 3, "V": [0, "", "(L.) Skeels"]}, {"N": 7, "V": [0, "", "Amla"]}, {"N": 48, "V": [1, 2, 1]}, {"N": 17, "V": [0, "", "25-30 feet"]}, {"N": 15, "V": [1, 1, 0]}], "CI": "Phyllanthus - Star Gooseberry Tree/Star Gooseberry Tree - Canopy.jpg"}, {"CN": 9, "CV": [{"N": 31, "V": [0, "", "<a href=\"http://en.wikipedia.org/wiki/Phyllanthus_acidus\" target=\"_blank\">wikipedia</a><br /><a href=\"http://www.flowersofindia.net/catalog/slides/Star%20Gooseberry.html\" target=\"_blank\">flowersofindia</a><br /><a href=\"http://www.ars-grin.gov/cgi-bin/npgs/html/taxon.pl?28113\" target=\"_blank\">ars-grin</a><br /><a href=\"http://www.theplantlist.org/tpl/record/kew-153279\" target=\"_blank\">theplantlist</a>"]}, {"N": 10, "V": [0, "", "Star Gooseberry is a small deciduous tree reaching about 25-30 ft in height. Leaves are compound, 14-25 inches long, crowded at the ends of the branches leaflets 2-3.5 inches long by 1-1.5 inches wide, alternately arranged along the rachis, ovate or obliquely ovate, acute or somewhat acuminate, base rounded or somewhat wedge-shaped. The genus name Phyllanthus is derived from Greek words meaning leaf-flower, an allusion to the apparent bearing of flowers on the leaves. The species name acidus is on account of the acidity of the fruit. Flowers are very minute, in short dense spike-like clusters arising from nodules along the branches, like mulberries. Fruit is pendulous, in small clusters from the branches, round or slightly flattened at the poles, with shallow or deep ribs (usually 5) 0.75 inch across. The tree usually flowers and produces fruit twice a year. Fruits appear simultaneously with the flowers. So, the tree usally has fruits hanging from it, at any time of the year. The fruit is used chiefly for pickling and for the preparation of preserves. It makes an excellent jam. Star Gooseberry is native of Malay Islands and Madagascar and frequently grown in India for its acid fruit."]}, {"N": 38, "V": [0, "", ["India"]]}]}, {"CN": 7, "CV": [{"N": 11, "V": [0, "", "<i>Otaheite gooseberry, Malay gooseberry, Tahitian gooseberry, Country gooseberry, Star gooseberry, Starberry, West india gooseberry, Gooseberry tree</i>"]}, {"N": 4, "V": [0, "", "<i>\u0985\u09b0\u09ac\u09a1\u09bc\u0987, \u0985\u09b0\u09ac\u09b0\u0987</i>"]}, {"N": 18, "V": [0, "", "<i>\u0939\u0930\u095e\u0930\u094c\u0930\u0940 \u092a\u0947\u0921\u093c, Harfarauri</i>"]}, {"N": 20, "V": [0, "", "<i>\u0c95\u0cbf\u0cb0\u0cc1\u0ca8\u0cc6\u0cb2\u0ccd\u0cb2\u0cbf, \u0cb0\u0cbe\u0caf\u0cb0\u0ca8\u0cc6\u0cb2\u0ccd\u0cb2\u0cbf, Kirunelli, Raayaranelli</i>"]}, {"N": 23, "V": [0, "", "<i>Rajamvali</i>"]}, {"N": 32, "V": [0, "", "<i>\u0d05\u0d30\u0d3f\u0d28\u0d46\u0d32\u0d4d\u0d32\u0d3f, \u0d05\u0d30\u0d3f\u0d28\u0d46\u0d32\u0d4d\u0d32\u0d3f\u0d15\u0d4d\u0d15, \u0d2a\u0d41\u0d33\u0d3f\u0d28\u0d46\u0d32\u0d4d\u0d32\u0d3f\u0d15\u0d4d\u0d15, \u0d36\u0d40\u0d2e\u0d28\u0d46\u0d32\u0d4d\u0d32\u0d3f\u0d15\u0d4d\u0d15, \u0d28\u0d46\u0d32\u0d4d\u0d32\u0d3f\u0d2a\u0d4d\u0d2a\u0d41\u0d33\u0d3f, \u0d28\u0d15\u0d4d\u0d37\u0d24\u0d4d\u0d30\u0d28\u0d46\u0d32\u0d4d\u0d32\u0d3f\u0d15\u0d4d\u0d15, \u0d2a\u0d41\u0d33\u0d3f\u0d28\u0d46\u0d32\u0d4d\u0d32\u0d3f, Otaheite gooseberry</i>"]}, {"N": 33, "V": [0, "", "<i>\u0997\u09bf\u09b9\u09cb\u09f0\u09c0, Gihori</i>"]}, {"N": 34, "V": [0, "", "<i>\u0930\u093e\u092f\u0906\u0902\u0935\u0933\u093e, \u0930\u093e\u092f\u0906\u0935\u0933\u093e, \u0939\u0930\u095e\u0930\u094c\u0930\u0940, Harpharori</i>"]}, {"N": 54, "V": [0, "", "<i>\u0b85\u0bb0\u0bc1\u0ba8\u0bc6\u0bb2\u0bcd\u0bb2\u0bbf \u0bae\u0bb0\u0bae\u0bcd, Aranelli</i>"]}, {"N": 56, "V": [0, "", "<i>\u0c30\u0c3e\u0c1a \u0c09\u0c38\u0c3f\u0c30\u0c3f</i>"]}, {"N": 61, "V": [0, "", "<i>Harfarauri</i>"]}]}, {"CN": 0, "CV": [{"N": 5, "V": [1, 0, 6]}, {"N": 57, "V": [0, "", "Rough"]}], "CI": "Phyllanthus - Star Gooseberry Tree/Star Gooseberry Tree - Bark.jpg"}, {"CN": 3, "CV": [{"N": 48, "V": [0, "", "Small"]}, {"N": 46, "V": [0, "", "Cup"]}, {"N": 5, "V": [1, 0, 8]}, {"N": 44, "V": [0, "", "Mar-May"]}], "CI": "Phyllanthus - Star Gooseberry Tree/Star Gooseberry Tree - Flower.jpg"}, {"CN": 4, "CV": [{"N": 48, "V": [0, "", "2 cm"]}, {"N": 46, "V": [0, "", "Round"]}, {"N": 5, "V": [1, 0, 13]}, {"N": 19, "V": [0, "", "Color: Yellow Green; deep ribs"]}], "CI": "Phyllanthus - Star Gooseberry Tree/Star Gooseberry Tree - Fruit.jpg"}, {"CN": 8, "CV": [{"N": 60, "V": [1, 4, 3]}, {"N": 48, "V": [0, "", "Large"]}, {"N": 57, "V": [0, "", "Feathery"]}, {"N": 46, "V": [0, "", "Oval"]}, {"N": 27, "V": [0, "", "Many pairs"]}, {"N": 30, "V": [0, "", "Even"]}, {"N": 19, "V": [0, "", "Tiny point at apex"]}], "CI": "Phyllanthus - Star Gooseberry Tree/Star Gooseberry Tree - Leaf.jpg"}], "mapinfo": [{"lat": "12.98092731", "long": "77.63377656"}, {"lat": "12.94927201", "long": "77.58291009"}, {"lat": "12.94930073", "long": "77.58294781"}, {"lat": "12.9636590644", "long": "77.6016546486"}, {"lat": "12.9635161461", "long": "77.6016465722"}, {"lat": "12.9342599751", "long": "77.6206846313"}, {"lat": "12.9725597852", "long": "77.6402638251"}, {"lat": "12.9735993596", "long": "77.6371854179"}, {"lat": "12.9805342785", "long": "77.6463042667"}, {"lat": "12.969940517383026", "long": "77.62821342245661"}, {"lat": "12.998076432572352", "long": "77.56486458850532"}, {"lat": "12.972090711406448", "long": "77.6391583680977"}, {"lat": "12.971026114957608", "long": "77.64499806418132"}, {"lat": "12.971237388438025", "long": "77.64530105963951"}, {"lat": "12.971443674269148", "long": "77.64588415738172"}, {"lat": "12.97089862984626", "long": "77.64694600431346"}, {"lat": "12.973005055553156", "long": "77.6427630602276"}, {"lat": "12.977348935420794", "long": "77.64406933050083"}, {"lat": "12.965190949352364", "long": "77.64063756217939"}, {"lat": "12.976452068856258", "long": "77.63122796427155"}, {"lat": "12.978317689994624", "long": "77.62709844422977"}, {"lat": "12.976584721775904", "long": "77.62651065077074"}, {"lat": "12.979716208693782", "long": "77.63735150298402"}, {"lat": "12.97758333270322", "long": "77.63028920806215"}, {"lat": "12.980651575425062", "long": "77.62861464025639"}, {"lat": "12.963946482801777", "long": "77.63613426217984"}, {"lat": "12.964563009095675", "long": "77.63559549626717"}, {"lat": "12.963406358541807", "long": "77.63423324802096"}, {"lat": "12.961774795729443", "long": "77.6365116594763"}, {"lat": "12.991145548663798", "long": "77.66153136127525"}, {"lat": "12.96315829423401", "long": "77.64010868450316"}, {"lat": "12.963842861222263", "long": "77.63560090155619"}, {"lat": "12.978438674200989", "long": "77.62300004989152"}, {"lat": "12.970061966331969", "long": "77.61732773819341"}, {"lat": "12.965830740795798", "long": "77.61711574152037"}, {"lat": "12.969223184900429", "long": "77.62661276565706"}, {"lat": "12.963432816147652", "long": "77.64407857923777"}, {"lat": "12.965237192620105", "long": "77.64256989381147"}, {"lat": "12.96461675", "long": "77.64262679"}, {"lat": "12.964584582763818", "long": "77.64299398669067"}, {"lat": "12.961907417147076", "long": "77.64412689835046"}, {"lat": "12.97361835138972", "long": "77.60445257196102"}, {"lat": "12.960740532490112", "long": "77.63577168350793"}, {"lat": "12.973893707790738", "long": "77.6069688187169"}, {"lat": "12.97149516", "long": "77.6570597"}, {"lat": "12.967166325255409", "long": "77.65785897678677"}, {"lat": "12.967112527816052", "long": "77.65782693237446"}, {"lat": "12.959510908854513", "long": "77.63600658806808"}, {"lat": "12.9600599023945", "long": "77.63974845106407"}, {"lat": "12.960096946519286", "long": "77.63908137277707"}, {"lat": "12.959702571181078", "long": "77.63896970622329"}, {"lat": "12.959548230013214", "long": "77.63897323861943"}, {"lat": "12.959402692934296", "long": "77.63894769253909"}, {"lat": "12.968981318072448", "long": "77.64994572626114"}, {"lat": "12.971632202039771", "long": "77.65121076456336"}, {"lat": "12.972143257076528", "long": "77.65144960853007"}, {"lat": "12.98197460421636", "long": "77.64284170438202"}, {"lat": "12.973706039323405", "long": "77.64968068352835"}, {"lat": "12.97257145485527", "long": "77.65635134891443"}, {"lat": "12.97193805599706", "long": "77.65715977386958"}, {"lat": "12.969826232770917", "long": "77.65454871262523"}, {"lat": "12.97348277026886", "long": "77.64715756379968"}, {"lat": "12.968156775608664", "long": "77.64963878501356"}, {"lat": "12.970064185007015", "long": "77.60314882352452"}, {"lat": "12.970931360820872", "long": "77.59888828112037"}, {"lat": "12.964336616380416", "long": "77.60265732512204"}, {"lat": "12.96525412136473", "long": "77.61020758018253"}, {"lat": "12.963075242833584", "long": "77.61323158545548"}, {"lat": "12.966129102888297", "long": "77.61416898487596"}, {"lat": "12.955246161118938", "long": "77.61476112214581"}, {"lat": "12.960830734631154", "long": "77.61565186501434"}, {"lat": "12.95777423359206", "long": "77.6154916990763"}, {"lat": "12.959135685540314", "long": "77.61673064601604"}, {"lat": "12.95928461323807", "long": "77.61588600424255"}, {"lat": "12.961159398483698", "long": "77.61368397347633"}, {"lat": "12.95653207845263", "long": "77.6178992682938"}, {"lat": "12.956327076744282", "long": "77.61606043716881"}, {"lat": "12.96477827871684", "long": "77.60322249416754"}, {"lat": "12.964207801990135", "long": "77.60152158581008"}, {"lat": "12.978685902638661", "long": "77.59246828104631"}, {"lat": "12.982094939022591", "long": "77.65010009912328"}, {"lat": "12.981187342169664", "long": "77.64686631908307"}, {"lat": "12.980475263597194", "long": "77.60578640542661"}, {"lat": "12.983773209196574", "long": "77.6004762090505"}, {"lat": "12.98837640511167", "long": "77.59886165730086"}, {"lat": "12.986132657871858", "long": "77.59577691296818"}, {"lat": "12.962596649025047", "long": "77.59204549065083"}, {"lat": "12.995644710986092", "long": "77.61642874311451"}, {"lat": "12.984833714309469", "long": "77.64541718062526"}, {"lat": "12.981320687106802", "long": "77.65705016142078"}, {"lat": "12.996692856258449", "long": "77.61772970820243"}, {"lat": "12.997846965035906", "long": "77.61982009599564"}, {"lat": "12.989575230631841", "long": "77.61827034143772"}, {"lat": "12.974203854856452", "long": "77.65283921827188"}, {"lat": "12.997699087874569", "long": "77.61645528412623"}, {"lat": "12.965223579565107", "long": "77.60063475937045"}, {"lat": "12.996786776807166", "long": "77.62203598953295"}, {"lat": "12.942864979884824", "long": "77.62214407847199"}, {"lat": "12.942791276829436", "long": "77.61333951315584"}, {"lat": "12.949939223021058", "long": "77.60345212201133"}, {"lat": "12.97147105418262", "long": "77.66063627091842"}, {"lat": "12.971364689229896", "long": "77.666311748162"}, {"lat": "12.965832205653877", "long": "77.66242429453501"}, {"lat": "12.960476465836928", "long": "77.65759918108859"}, {"lat": "12.990136440102837", "long": "77.6048542933346"}, {"lat": "13.000879608333598", "long": "77.61884675200491"}, {"lat": "12.959723922137231", "long": "77.66794268571527"}, {"lat": "12.961289353726514", "long": "77.66837814024058"}, {"lat": "12.966503138283915", "long": "77.59073409853266"}, {"lat": "12.953699320977709", "long": "77.59208061417996"}, {"lat": "12.943983546416028", "long": "77.579722110023"}, {"lat": "12.943536526933508", "long": "77.57818562886342"}, {"lat": "12.960290423646219", "long": "77.66764736714168"}, {"lat": "12.95672658986997", "long": "77.65606140335035"}, {"lat": "12.976126765655401", "long": "77.56986899116458"}, {"lat": "12.976119716338706", "long": "77.56996451241719"}, {"lat": "12.978776596633628", "long": "77.57381544944712"}, {"lat": "12.954514811385117", "long": "77.57989318024062"}, {"lat": "12.948530240242334", "long": "77.57492737857831"}, {"lat": "12.949393949138317", "long": "77.57141424837755"}, {"lat": "12.955642201346697", "long": "77.56771036576316"}, {"lat": "12.953196114429225", "long": "77.5686408704496"}, {"lat": "12.954697581573482", "long": "77.56876005325466"}, {"lat": "12.944874420254765", "long": "77.568787530181"}, {"lat": "12.998701488429877", "long": "77.5642793342397"}, {"lat": "12.994169578052835", "long": "77.56838370590464"}, {"lat": "13.001937550002843", "long": "77.57061364303809"}, {"lat": "12.998942981216295", "long": "77.56615172547754"}, {"lat": "13.00097084170633", "long": "77.5653418712318"}, {"lat": "12.999904390854269", "long": "77.56696725060465"}, {"lat": "13.000936617002852", "long": "77.57048355590086"}, {"lat": "13.001546174995376", "long": "77.57058985414915"}, {"lat": "12.94812724027593", "long": "77.57435640902258"}, {"lat": "12.94447623867848", "long": "77.57574919582112"}, {"lat": "12.94583267506462", "long": "77.57617011404363"}, {"lat": "12.946012671310722", "long": "77.5764292065287"}, {"lat": "13.005781093988013", "long": "77.56357251957525"}, {"lat": "13.00802238208312", "long": "77.56251094629988"}, {"lat": "13.004007336591515", "long": "77.56823764852015"}, {"lat": "13.007182815548395", "long": "77.56379437021678"}, {"lat": "12.98068963479388", "long": "77.57930799212772"}, {"lat": "13.008266930594143", "long": "77.5697488851871"}, {"lat": "12.946816019449386", "long": "77.57792536391018"}, {"lat": "12.941440688906646", "long": "77.5675017621436"}, {"lat": "12.942844754929355", "long": "77.57281194429545"}, {"lat": "12.943223274640813", "long": "77.57826077197511"}, {"lat": "12.990774698518928", "long": "77.57318469228548"}, {"lat": "12.939261870872347", "long": "77.57390846513621"}, {"lat": "12.957932547969953", "long": "77.56392005341637"}, {"lat": "12.958364986044508", "long": "77.56086957980735"}, {"lat": "12.936034027011486", "long": "77.58219213326358"}, {"lat": "12.933917151815765", "long": "77.58150467866473"}, {"lat": "12.991830233264873", "long": "77.57548686429118"}, {"lat": "12.930297040829418", "long": "77.58555831429477"}, {"lat": "13.01067208749626", "long": "77.55912969975954"}, {"lat": "12.927701265092596", "long": "77.57822961941885"}, {"lat": "12.929180622844141", "long": "77.58357907272284"}, {"lat": "12.930012265957263", "long": "77.58348231058791"}, {"lat": "12.925412321035315", "long": "77.5829898070856"}, {"lat": "12.922764242998257", "long": "77.57652938228377"}, {"lat": "12.9227723960392", "long": "77.57675869124343"}, {"lat": "12.921881824343432", "long": "77.5814989799119"}, {"lat": "12.919768986852377", "long": "77.57673453274039"}, {"lat": "12.92054966608402", "long": "77.57450413801963"}, {"lat": "12.920180081352632", "long": "77.57466961463251"}, {"lat": "12.91992070344389", "long": "77.58405269891455"}, {"lat": "12.920573262610167", "long": "77.58407846823276"}, {"lat": "12.921316073270766", "long": "77.58460201981053"}, {"lat": "12.918741330973095", "long": "77.58424345144705"}, {"lat": "12.919268591333845", "long": "77.5826239689559"}, {"lat": "12.924590957722359", "long": "77.5859321071289"}, {"lat": "12.935207768430752", "long": "77.57374051256875"}, {"lat": "12.935044809895178", "long": "77.57374812044533"}, {"lat": "12.935088877679892", "long": "77.57374665006184"}, {"lat": "12.934974233543445", "long": "77.57374769536455"}, {"lat": "13.002881511957384", "long": "77.55056627203773"}, {"lat": "12.939107034011416", "long": "77.57444627286759"}, {"lat": "12.934248624188971", "long": "77.57835827471582"}, {"lat": "12.932339384820981", "long": "77.57958843794087"}, {"lat": "12.990186930179835", "long": "77.55236721944813"}, {"lat": "12.980259821955682", "long": "77.56417098430006"}, {"lat": "12.974345477214127", "long": "77.6256872759268"}, {"lat": "12.980367559010915", "long": "77.55330978719485"}, {"lat": "12.986657649406132", "long": "77.55730499280503"}, {"lat": "12.989566421960419", "long": "77.55401780338389"}, {"lat": "12.989670445387855", "long": "77.55411607188763"}, {"lat": "12.98952221011318", "long": "77.55563185433631"}, {"lat": "12.975437657940805", "long": "77.55162046533998"}, {"lat": "12.983322803475948", "long": "77.54990383540418"}, {"lat": "12.986658754242244", "long": "77.55157061328532"}, {"lat": "12.986679212178688", "long": "77.55156184700355"}, {"lat": "12.976091506549269", "long": "77.55191048819371"}, {"lat": "12.983130743075296", "long": "77.5550035313222"}, {"lat": "12.988537961490838", "long": "77.57591672682906"}, {"lat": "12.980963832857222", "long": "77.55705609983353"}, {"lat": "12.986170839892614", "long": "77.55942168578144"}, {"lat": "12.986842532580434", "long": "77.55929233264398"}, {"lat": "12.983049251716567", "long": "77.55235334850853"}, {"lat": "12.983884166998148", "long": "77.55054476900797"}, {"lat": "12.971927250028168", "long": "77.54310599794962"}, {"lat": "12.967582026046072", "long": "77.53652440884936"}, {"lat": "12.963755070443876", "long": "77.53568069996166"}, {"lat": "12.973853789376168", "long": "77.54902682452554"}, {"lat": "12.982521637400358", "long": "77.55082125778928"}, {"lat": "12.982354229165392", "long": "77.55067300420707"}, {"lat": "12.977110075770943", "long": "77.55088644243416"}, {"lat": "12.978152311348966", "long": "77.55200525547252"}, {"lat": "12.980094895313927", "long": "77.55179163329787"}, {"lat": "12.974670264053211", "long": "77.53508558800833"}, {"lat": "12.974531433018104", "long": "77.53547836718326"}, {"lat": "12.941564414252259", "long": "77.57076212452375"}, {"lat": "12.941383804878821", "long": "77.57236171546538"}, {"lat": "12.9392697124146", "long": "77.56976751471484"}, {"lat": "12.938025737875492", "long": "77.57474905051822"}, {"lat": "12.9363215057748", "long": "77.57450664622638"}, {"lat": "12.926508911098608", "long": "77.57488192670509"}, {"lat": "12.925694659636793", "long": "77.5740498739424"}, {"lat": "12.925558350353445", "long": "77.57388728085972"}, {"lat": "12.973332015366662", "long": "77.57419259528433"}, {"lat": "12.984350950474042", "long": "77.55879555220193"}, {"lat": "12.982033196113973", "long": "77.55105824298425"}, {"lat": "12.968931110267546", "long": "77.54247404556737"}, {"lat": "12.964789464655516", "long": "77.54161756080522"}, {"lat": "12.922353525415677", "long": "77.5741028556331"}, {"lat": "12.965589240403391", "long": "77.54306228953739"}, {"lat": "12.930729220630846", "long": "77.61294443643921"}, {"lat": "13.001395249605606", "long": "77.55785157618904"}, {"lat": "13.00464169008903", "long": "77.55713429034358"}, {"lat": "12.962898742085484", "long": "77.5374098771522"}, {"lat": "13.001260183543845", "long": "77.56017519699073"}, {"lat": "13.005492749787642", "long": "77.55885550292534"}, {"lat": "12.958445302516592", "long": "77.53622759096517"}, {"lat": "12.962729068723005", "long": "77.53868182316182"}, {"lat": "12.963521932214967", "long": "77.53836642022863"}, {"lat": "13.006657643620917", "long": "77.54923678566458"}, {"lat": "12.960182717888992", "long": "77.53992762743565"}, {"lat": "12.960357209779815", "long": "77.53938115904704"}, {"lat": "13.008092177946862", "long": "77.55928889718918"}, {"lat": "13.008272223528943", "long": "77.55948432680725"}, {"lat": "13.009102369160802", "long": "77.55777623321366"}, {"lat": "12.974764835689015", "long": "77.56980998391101"}, {"lat": "12.975934687600972", "long": "77.55714520812036"}, {"lat": "12.951980267908693", "long": "77.57924881530813"}, {"lat": "12.95142251206262", "long": "77.57878363352575"}, {"lat": "12.95139145587207", "long": "77.57878154298169"}, {"lat": "13.010758257535912", "long": "77.54631153348328"}, {"lat": "12.921115608041642", "long": "77.58632175702589"}, {"lat": "12.989624766462429", "long": "77.57514419532981"}, {"lat": "12.986664415935241", "long": "77.57359214715281"}, {"lat": "12.985856979421644", "long": "77.5754791048098"}, {"lat": "12.926308290838893", "long": "77.58710014948292"}, {"lat": "12.986329344026753", "long": "77.57839268602993"}, {"lat": "12.985885483740606", "long": "77.57913914804023"}, {"lat": "12.9933248938641", "long": "77.57868943677296"}, {"lat": "12.983367375636192", "long": "77.56820375078179"}, {"lat": "12.983695339360438", "long": "77.5681757926941"}, {"lat": "12.98863528489324", "long": "77.56666887222538"}, {"lat": "12.99063247245571", "long": "77.59307625410658"}, {"lat": "12.99068786317623", "long": "77.59280713708223"}, {"lat": "12.990688088751257", "long": "77.59218701857208"}, {"lat": "12.992351217186139", "long": "77.59321048637732"}, {"lat": "12.992694231625903", "long": "77.59224773490133"}, {"lat": "12.98609204258428", "long": "77.59874978862172"}, {"lat": "12.988109543362906", "long": "77.59901776467588"}, {"lat": "12.988098039192352", "long": "77.59904008245486"}, {"lat": "12.991813094158157", "long": "77.59608368030969"}, {"lat": "12.99849860611259", "long": "77.5832059100867"}, {"lat": "13.003879278832944", "long": "77.54736341684067"}, {"lat": "13.010190254097521", "long": "77.54711720172965"}, {"lat": "13.011778263011134", "long": "77.54424777873284"}, {"lat": "12.927216848430817", "long": "77.59071448580245"}, {"lat": "12.924857123380578", "long": "77.59695762681078"}, {"lat": "12.923112507245534", "long": "77.59638656858671"}, {"lat": "12.928609403456052", "long": "77.59264565638208"}, {"lat": "12.925748720956422", "long": "77.5911771630922"}, {"lat": "12.924641177383442", "long": "77.59010677899597"}, {"lat": "12.921880102415656", "long": "77.59713831794897"}, {"lat": "12.923636368962026", "long": "77.5961965344709"}, {"lat": "12.926063625539626", "long": "77.59402109769553"}, {"lat": "12.936739421290017", "long": "77.6231548530359"}, {"lat": "12.93492957665138", "long": "77.61831252734284"}, {"lat": "12.935642404309188", "long": "77.61793508281472"}, {"lat": "12.934366269379339", "long": "77.62045002548804"}, {"lat": "12.929617168023446", "long": "77.63157668605118"}, {"lat": "12.931674392089393", "long": "77.62957262221789"}, {"lat": "12.933249543865697", "long": "77.62731495543221"}, {"lat": "12.934660426729565", "long": "77.62660037915568"}, {"lat": "12.936068236721214", "long": "77.62626787965702"}, {"lat": "12.93009448015834", "long": "77.62744232064053"}, {"lat": "12.933014889562909", "long": "77.62508415051798"}, {"lat": "12.932579935156182", "long": "77.62768112372214"}, {"lat": "12.92557182553418", "long": "77.62779534301218"}, {"lat": "12.927453984176632", "long": "77.62378034830363"}, {"lat": "12.928662632353173", "long": "77.62123762162675"}, {"lat": "12.93729840625557", "long": "77.61303357329327"}, {"lat": "12.94111337800177", "long": "77.61892997855172"}, {"lat": "12.93984872456068", "long": "77.61873000481047"}, {"lat": "12.939928983376051", "long": "77.61865608991002"}, {"lat": "12.92867370807636", "long": "77.63480298075139"}, {"lat": "12.920320500087406", "long": "77.59646466467758"}, {"lat": "12.919643894353221", "long": "77.59622693114808"}, {"lat": "13.001916386085776", "long": "77.66013543035115"}, {"lat": "13.004897268841198", "long": "77.65404161466678"}, {"lat": "12.995194024897875", "long": "77.65923703732142"}, {"lat": "12.996298124901577", "long": "77.66102917805483"}, {"lat": "12.918537959544292", "long": "77.59010483439853"}, {"lat": "12.91845429306004", "long": "77.59539311717278"}, {"lat": "12.917640777057068", "long": "77.59546912508314"}, {"lat": "12.917472441182285", "long": "77.59545990891866"}, {"lat": "12.918282381712093", "long": "77.59650489777187"}, {"lat": "12.999369327765706", "long": "77.6662086901854"}, {"lat": "12.92245984582296", "long": "77.57287137369077"}, {"lat": "12.922758538465223", "long": "77.57033799619194"}, {"lat": "12.92885109777582", "long": "77.57285452346652"}, {"lat": "12.925384341003236", "long": "77.5728438344322"}, {"lat": "12.948983468356989", "long": "77.57057439348729"}, {"lat": "12.950611532580199", "long": "77.57187447193475"}, {"lat": "12.951619161280531", "long": "77.56818340925749"}, {"lat": "12.94805151853224", "long": "77.56435450493427"}, {"lat": "12.950985397147464", "long": "77.56599413137339"}, {"lat": "12.951300119412256", "long": "77.56204556048489"}, {"lat": "12.94944462168493", "long": "77.56174256160195"}, {"lat": "12.9454022295713", "long": "77.56656148940465"}, {"lat": "12.945506379036459", "long": "77.56617459628616"}, {"lat": "12.933255807079394", "long": "77.51689832006832"}, {"lat": "12.927974523131796", "long": "77.51125984192187"}, {"lat": "12.910428747916757", "long": "77.5842935259516"}, {"lat": "12.955517093164723", "long": "77.54897811784076"}, {"lat": "12.931138905929368", "long": "77.51580865957978"}, {"lat": "12.9275999482274", "long": "77.56851026466167"}, {"lat": "12.926581819909558", "long": "77.57242591445903"}, {"lat": "12.923095468274512", "long": "77.56996238127613"}, {"lat": "12.922610527652953", "long": "77.56969060567826"}, {"lat": "12.931001715326937", "long": "77.51715828426315"}, {"lat": "12.930979549174266", "long": "77.51718975736823"}, {"lat": "12.92999455409667", "long": "77.51686460701421"}, {"lat": "12.930100022588782", "long": "77.51660598537684"}, {"lat": "12.93288078780408", "long": "77.51578681907404"}, {"lat": "12.932567185225334", "long": "77.51522002408933"}, {"lat": "12.932445608447383", "long": "77.51514503285307"}, {"lat": "12.92882634855247", "long": "77.51419835971319"}, {"lat": "12.925922734097698", "long": "77.56888845613278"}, {"lat": "12.926041585468724", "long": "77.56881359789988"}, {"lat": "12.92705538504382", "long": "77.56555436714963"}, {"lat": "12.928276347344", "long": "77.56628835401898"}, {"lat": "12.934645745620772", "long": "77.568438768501"}, {"lat": "12.933665279454678", "long": "77.56147133532978"}, {"lat": "12.930505246082184", "long": "77.60816824255016"}, {"lat": "12.9232870023706", "long": "77.56844844708213"}, {"lat": "12.923358459448444", "long": "77.56844469597581"}, {"lat": "12.948397920917566", "long": "77.56155287051799"}, {"lat": "12.948942867155052", "long": "77.55709746902768"}, {"lat": "12.948001606098234", "long": "77.55896326857966"}, {"lat": "12.95013990260876", "long": "77.59622178673455"}, {"lat": "12.948272195594898", "long": "77.59707139199237"}, {"lat": "12.94738828116177", "long": "77.5978891264549"}, {"lat": "12.950494377556524", "long": "77.59698948274946"}, {"lat": "12.9281916899357", "long": "77.56330137495297"}, {"lat": "12.927873304645368", "long": "77.564611929879"}, {"lat": "12.92837352780627", "long": "77.56425856813848"}, {"lat": "12.911834646023731", "long": "77.58999467558398"}, {"lat": "12.922745705060272", "long": "77.56344063982398"}, {"lat": "12.924863974600619", "long": "77.5621787325349"}, {"lat": "12.938893190468379", "long": "77.5662080058237"}, {"lat": "12.938574040515897", "long": "77.56378160475835"}, {"lat": "12.942705705051004", "long": "77.56739430969677"}, {"lat": "13.002367968138888", "long": "77.57679665172874"}, {"lat": "12.935713491808514", "long": "77.57448942063776"}, {"lat": "12.993109621247793", "long": "77.57529472215539"}, {"lat": "12.917216017640293", "long": "77.59770032277629"}, {"lat": "13.001227132196789", "long": "77.57952108318933"}, {"lat": "13.00321486869053", "long": "77.58271077142128"}, {"lat": "13.003780513860939", "long": "77.58277475313209"}, {"lat": "12.921781128128549", "long": "77.56704902001957"}, {"lat": "12.922849438194259", "long": "77.5627445754799"}, {"lat": "12.921293755145443", "long": "77.56648429700817"}, {"lat": "12.921492826147457", "long": "77.56610255575198"}, {"lat": "12.919181462163465", "long": "77.56630936179818"}, {"lat": "12.999219315015452", "long": "77.58236951831805"}, {"lat": "12.908112078429896", "long": "77.5805252708983"}, {"lat": "12.90956313905884", "long": "77.58060608580764"}, {"lat": "12.906800439943844", "long": "77.58534774470037"}, {"lat": "12.939266108588521", "long": "77.5866943044025"}, {"lat": "12.983613668046624", "long": "77.54451452809462"}, {"lat": "12.998746484063778", "long": "77.54786882802365"}, {"lat": "12.998821346159435", "long": "77.54701366819974"}, {"lat": "12.915217908076341", "long": "77.60256171226503"}, {"lat": "12.91501627370155", "long": "77.602769610844"}, {"lat": "13.007996707922258", "long": "77.5446795795756"}, {"lat": "12.976608598740377", "long": "77.54090450047444"}, {"lat": "12.976726028194893", "long": "77.54137667035138"}, {"lat": "12.971775544508802", "long": "77.53736289122344"}, {"lat": "12.976868851883928", "long": "77.53988469222124"}, {"lat": "12.978258296139986", "long": "77.53936518006185"}, {"lat": "12.978884645850032", "long": "77.53955691830699"}, {"lat": "12.976865072686872", "long": "77.53567320147341"}, {"lat": "12.97847562858743", "long": "77.53708804810687"}, {"lat": "12.995475305325936", "long": "77.565518031804"}, {"lat": "12.994300818337228", "long": "77.56700661305332"}, {"lat": "12.993397334323907", "long": "77.5658428587508"}, {"lat": "13.000325631189174", "long": "77.54627471585081"}, {"lat": "13.004301001482382", "long": "77.5450807854793"}, {"lat": "12.996016508299268", "long": "77.55943704141374"}, {"lat": "13.001514026918892", "long": "77.54755155798877"}, {"lat": "13.002082145244032", "long": "77.54732562538494"}, {"lat": "13.003678962792495", "long": "77.54463043471333"}, {"lat": "12.991938416610283", "long": "77.5589437237045"}, {"lat": "12.91767828494208", "long": "77.61026655902243"}, {"lat": "12.91561086900267", "long": "77.60860790852804"}, {"lat": "13.000237056347968", "long": "77.54574280139083"}, {"lat": "12.917467055992095", "long": "77.60391920955273"}, {"lat": "12.918546486721821", "long": "77.61822081888569"}, {"lat": "12.91888904196553", "long": "77.6200013407788"}, {"lat": "12.908494881209567", "long": "77.57041745694096"}, {"lat": "12.99220204270738", "long": "77.54779419599573"}, {"lat": "12.99225356126112", "long": "77.54807032930331"}, {"lat": "12.993042854978821", "long": "77.5504870406553"}, {"lat": "12.914841006942838", "long": "77.61721434420225"}, {"lat": "12.915460785895034", "long": "77.61745758000303"}, {"lat": "12.915407526359107", "long": "77.61408976827624"}, {"lat": "12.98361926101291", "long": "77.54664277008943"}, {"lat": "12.983974756153296", "long": "77.5470518033012"}, {"lat": "13.010573857066264", "long": "77.55029574990887"}, {"lat": "12.911403752719078", "long": "77.59768368512825"}, {"lat": "12.912565727347921", "long": "77.59653097408547"}, {"lat": "12.911618677103728", "long": "77.59600978536129"}, {"lat": "12.914755581289098", "long": "77.5981744821172"}, {"lat": "13.017858570104702", "long": "77.55327830668193"}, {"lat": "13.016048213246409", "long": "77.55582918183336"}, {"lat": "12.913246624358834", "long": "77.59700068885878"}, {"lat": "12.90699239321101", "long": "77.59518807980841"}, {"lat": "12.960986801305971", "long": "77.5298668465962"}, {"lat": "12.908302704437853", "long": "77.59580925107002"}, {"lat": "12.907452530131431", "long": "77.59340138057952"}, {"lat": "13.01250320948421", "long": "77.54846075970363"}, {"lat": "12.965511721893645", "long": "77.63457410555931"}, {"lat": "12.948656595870991", "long": "77.53852120277317"}, {"lat": "12.942408175267152", "long": "77.5488707909267"}, {"lat": "12.912588758769107", "long": "77.62373145332278"}, {"lat": "12.995089972420677", "long": "77.54485406481082"}, {"lat": "12.996028473076949", "long": "77.54342832037311"}, {"lat": "12.988368560422401", "long": "77.53817370263505"}, {"lat": "12.932829561203556", "long": "77.54148836485912"}, {"lat": "12.95964686720482", "long": "77.6809059887546"}, {"lat": "12.974481414426775", "long": "77.67156229610238"}, {"lat": "12.942348928957054", "long": "77.53613365272942"}, {"lat": "12.91157719513867", "long": "77.58276755412909"}, {"lat": "12.911149119856862", "long": "77.58206738690889"}, {"lat": "12.910217145570824", "long": "77.58510123382848"}, {"lat": "12.90783789385358", "long": "77.58246441723941"}, {"lat": "12.96224392942867", "long": "77.52355325802456"}, {"lat": "12.961793525376565", "long": "77.52054667496397"}, {"lat": "12.91115500427198", "long": "77.592244299467"}, {"lat": "12.910630132996545", "long": "77.59221367408828"}, {"lat": "12.907387227783232", "long": "77.59239711830107"}, {"lat": "12.908155582437466", "long": "77.59022972430557"}, {"lat": "12.91854579425236", "long": "77.61587166119172"}, {"lat": "12.918606273135381", "long": "77.61594758461798"}, {"lat": "12.918466818543076", "long": "77.61571577365204"}, {"lat": "12.91839105437668", "long": "77.61528733854449"}, {"lat": "12.9186867171844", "long": "77.61495194808731"}, {"lat": "12.91861227511338", "long": "77.61487682635448"}, {"lat": "12.910704367425396", "long": "77.59303402857086"}, {"lat": "12.910754683164052", "long": "77.59025869043172"}, {"lat": "12.912595959800559", "long": "77.59029191354558"}, {"lat": "12.912883992069965", "long": "77.58962567422714"}, {"lat": "12.912985283892501", "long": "77.58905016761902"}, {"lat": "12.908212229098625", "long": "77.57815119650331"}, {"lat": "12.907301381222556", "long": "77.58726447890469"}, {"lat": "12.90702852606147", "long": "77.58839596836425"}, {"lat": "12.909846863970479", "long": "77.58963273149902"}, {"lat": "12.916555674606489", "long": "77.59096063749668"}, {"lat": "12.915950066506952", "long": "77.59060944956673"}, {"lat": "12.92786512735959", "long": "77.55587386095843"}, {"lat": "12.910361812571711", "long": "77.57982794376404"}, {"lat": "12.94014503520323", "long": "77.53878721133107"}, {"lat": "12.991883710324533", "long": "77.59221079671761"}, {"lat": "12.960098288052649", "long": "77.60252519763753"}, {"lat": "12.961890979522652", "long": "77.60173925221807"}, {"lat": "12.961891833666362", "long": "77.60170095555624"}, {"lat": "12.961805788306961", "long": "77.60166397265948"}, {"lat": "12.958843141401736", "long": "77.60241317282636"}, {"lat": "12.957887522310918", "long": "77.59779560078643"}, {"lat": "12.940478021455453", "long": "77.55385404217577"}, {"lat": "12.940055659530364", "long": "77.55514351829335"}, {"lat": "12.94013123441457", "long": "77.55551097347961"}, {"lat": "12.962353778102932", "long": "77.6445602338356"}, {"lat": "12.962001020300011", "long": "77.64499112303385"}, {"lat": "12.961382854376529", "long": "77.64732582442095"}, {"lat": "12.938701782291838", "long": "77.56121308635558"}, {"lat": "12.937096910577553", "long": "77.56160653829285"}, {"lat": "12.93638822053371", "long": "77.56137614054525"}, {"lat": "12.989381156870962", "long": "77.5403551912018"}, {"lat": "12.991596876479047", "long": "77.54036880360901"}, {"lat": "12.988908738748862", "long": "77.53717323122375"}, {"lat": "12.992483648412167", "long": "77.54002602590391"}, {"lat": "12.955939434496193", "long": "77.64851997540065"}, {"lat": "12.935385391404585", "long": "77.56913082440862"}, {"lat": "12.994220463002797", "long": "77.5418339559451"}, {"lat": "12.994054805750228", "long": "77.54133024502381"}, {"lat": "12.939552037834448", "long": "77.56310583820778"}, {"lat": "12.934274360469718", "long": "77.56343392930832"}, {"lat": "12.98548220444181", "long": "77.54352603953068"}, {"lat": "12.988366185031333", "long": "77.545156499491"}, {"lat": "12.988179661463628", "long": "77.544042330469"}, {"lat": "12.994991800221257", "long": "77.54358597912189"}, {"lat": "12.992516463572224", "long": "77.54322782095187"}, {"lat": "12.983849478555223", "long": "77.53994753893721"}, {"lat": "12.969477734792582", "long": "77.62456902592477"}, {"lat": "12.940326751546905", "long": "77.54926125245221"}, {"lat": "12.984324459852719", "long": "77.53763780955411"}, {"lat": "12.981573584245815", "long": "77.54056267209764"}, {"lat": "12.937824980115055", "long": "77.54617310764162"}, {"lat": "13.00817009349282", "long": "77.57939069644408"}, {"lat": "12.933818331643325", "long": "77.54116122235018"}, {"lat": "12.933759976717925", "long": "77.54187980207008"}, {"lat": "12.93111415263029", "long": "77.54343820899295"}, {"lat": "12.93706390636474", "long": "77.54718994950737"}, {"lat": "12.936159570775219", "long": "77.54749172034735"}, {"lat": "12.936659591121334", "long": "77.54805912321446"}, {"lat": "12.940132848779689", "long": "77.54259181793714"}, {"lat": "12.980073236724603", "long": "77.62495104554773"}, {"lat": "12.980353393247372", "long": "77.62531949882715"}, {"lat": "12.981119768860486", "long": "77.62530722748353"}, {"lat": "12.981146282147689", "long": "77.625862905918"}, {"lat": "12.980668085544965", "long": "77.62654464874913"}, {"lat": "12.974518010805104", "long": "77.53385824207272"}, {"lat": "12.974886346846564", "long": "77.53195014618088"}, {"lat": "12.978727688748657", "long": "77.62388084791611"}, {"lat": "12.979336636405433", "long": "77.62256814772627"}, {"lat": "12.978033188171082", "long": "77.62191192130332"}, {"lat": "12.977996522848263", "long": "77.62183574680876"}, {"lat": "12.97813131565912", "long": "77.62166685092782"}, {"lat": "12.977837107642493", "long": "77.62148178969939"}, {"lat": "12.977984633827692", "long": "77.6212073728607"}, {"lat": "12.978606424087964", "long": "77.62265987476441"}, {"lat": "12.940358841264867", "long": "77.5434386191455"}, {"lat": "12.940003951711025", "long": "77.54359825036319"}, {"lat": "12.938916832733346", "long": "77.54465042450876"}, {"lat": "12.93727965180527", "long": "77.54439236942746"}, {"lat": "12.936914391012655", "long": "77.54326377463032"}, {"lat": "12.978362929473041", "long": "77.64467537178918"}, {"lat": "12.978387899539122", "long": "77.64405214477166"}, {"lat": "12.978384355705886", "long": "77.64397956727181"}, {"lat": "12.978343382555611", "long": "77.64399770175261"}, {"lat": "12.934538234971965", "long": "77.54402929681419"}, {"lat": "13.008699901911443", "long": "77.58309951666207"}, {"lat": "12.938403662297796", "long": "77.5424748659134"}, {"lat": "13.013305098862956", "long": "77.57404715119493"}, {"lat": "13.006537842110273", "long": "77.65907746453765"}, {"lat": "13.003557289003963", "long": "77.66076059543822"}, {"lat": "12.996314593254551", "long": "77.60533441413601"}, {"lat": "12.997051319911398", "long": "77.60011285915881"}, {"lat": "12.996405570927848", "long": "77.60302736760651"}, {"lat": "12.99634527729145", "long": "77.60323310469404"}, {"lat": "13.004673297250504", "long": "77.60378169104798"}, {"lat": "13.001481558646386", "long": "77.60182176190484"}, {"lat": "13.00156846739374", "long": "77.60123042553234"}, {"lat": "13.001578529646828", "long": "77.60057680674892"}, {"lat": "12.931156154404327", "long": "77.57262076740177"}, {"lat": "13.000711185656183", "long": "77.59502549413357"}, {"lat": "12.999749378881011", "long": "77.59894952992683"}, {"lat": "12.927172218904612", "long": "77.61571969871967"}, {"lat": "12.930126010885282", "long": "77.60975771240511"}, {"lat": "13.005600696067965", "long": "77.6153765810318"}, {"lat": "13.00566379032357", "long": "77.61584179272177"}, {"lat": "13.004725791523002", "long": "77.61762402363502"}, {"lat": "12.991655233417942", "long": "77.60016908738409"}, {"lat": "12.991242340003541", "long": "77.60046072612796"}, {"lat": "12.960855457155544", "long": "77.6584305127335"}, {"lat": "12.961090882690211", "long": "77.65723429099809"}, {"lat": "12.962101947763726", "long": "77.66011414146305"}, {"lat": "12.961827886484842", "long": "77.65808948569203"}, {"lat": "12.963221329943055", "long": "77.65842769630355"}, {"lat": "12.968174788362576", "long": "77.62816562586295"}, {"lat": "13.009756705695985", "long": "77.53983055832578"}, {"lat": "13.01807936875261", "long": "77.65315024500069"}, {"lat": "13.016854447382299", "long": "77.65091217646956"}, {"lat": "12.969982144408098", "long": "77.53277054112006"}, {"lat": "12.969019120841253", "long": "77.53162359408861"}, {"lat": "12.968805387143759", "long": "77.53125984026157"}, {"lat": "12.966712860879383", "long": "77.53421211966042"}, {"lat": "13.002572953981943", "long": "77.61926613214882"}, {"lat": "13.002499372537825", "long": "77.61933762456465"}, {"lat": "13.002380575158089", "long": "77.61931543609536"}, {"lat": "13.00234820774783", "long": "77.61930094870422"}, {"lat": "13.021582321674634", "long": "77.54148756808719"}, {"lat": "13.024744511105682", "long": "77.58275193196825"}, {"lat": "12.956063274371008", "long": "77.66194203891246"}, {"lat": "12.964564081423308", "long": "77.65676283749146"}, {"lat": "13.014331801175839", "long": "77.63973584280622"}, {"lat": "13.005966596703388", "long": "77.640080775127"}, {"lat": "13.005923271809138", "long": "77.63992386589963"}, {"lat": "13.005875859362229", "long": "77.63975683562649"}, {"lat": "12.963396861784702", "long": "77.52845225727243"}, {"lat": "12.962516243347071", "long": "77.52796790973436"}, {"lat": "12.962106700930223", "long": "77.52692920878191"}, {"lat": "12.962159977717555", "long": "77.52691890237656"}, {"lat": "12.962544399367243", "long": "77.526331912469"}, {"lat": "12.96158842524884", "long": "77.527069897983"}, {"lat": "12.958528524324096", "long": "77.52753604240526"}, {"lat": "13.04340042467224", "long": "77.55933353160118"}, {"lat": "13.042714826919036", "long": "77.55476640814095"}, {"lat": "13.03951974931396", "long": "77.5538972742561"}, {"lat": "12.976077483658125", "long": "77.5282740010198"}, {"lat": "13.012873194234633", "long": "77.53735952295075"}, {"lat": "13.028059312550832", "long": "77.53812790869235"}, {"lat": "12.931122941858389", "long": "77.54587101977904"}, {"lat": "13.012900138091208", "long": "77.5383789587454"}, {"lat": "13.013678050961614", "long": "77.53753226067376"}, {"lat": "12.926190137573437", "long": "77.55152020562265"}, {"lat": "12.930527355979786", "long": "77.54929518772089"}, {"lat": "13.009594545259807", "long": "77.53589611313373"}, {"lat": "13.004334051203106", "long": "77.53564374502845"}, {"lat": "12.931976025561786", "long": "77.54954695003107"}, {"lat": "12.934089761258162", "long": "77.54795313988099"}, {"lat": "12.966233172694702", "long": "77.56778460037141"}, {"lat": "12.93594721016926", "long": "77.54924380692046"}, {"lat": "12.934519976294697", "long": "77.54998578074493"}, {"lat": "12.971896087867542", "long": "77.52876388697815"}, {"lat": "12.971115219426444", "long": "77.52845276511836"}, {"lat": "12.968730385638882", "long": "77.5287352502346"}, {"lat": "12.983552693138517", "long": "77.67997976279277"}, {"lat": "12.984171282797034", "long": "77.67734394804165"}, {"lat": "12.984468233771343", "long": "77.67681643658763"}, {"lat": "12.984487727036559", "long": "77.6767120214845"}, {"lat": "12.984832042489911", "long": "77.67484870067166"}, {"lat": "12.98513683090501", "long": "77.67441191075477"}, {"lat": "12.98593973915791", "long": "77.67205867744224"}, {"lat": "12.986258961102934", "long": "77.67057277850428"}, {"lat": "12.926300800709436", "long": "77.55649332068288"}, {"lat": "12.966669229247197", "long": "77.52760003318144"}, {"lat": "12.95601208204362", "long": "77.56987460109943"}, {"lat": "12.932081000837968", "long": "77.56434693807707"}, {"lat": "12.92910387147697", "long": "77.56119347814548"}, {"lat": "12.928928756620634", "long": "77.56145160532016"}, {"lat": "12.928322852430757", "long": "77.55988758535636"}, {"lat": "12.928770801339638", "long": "77.56075520042032"}, {"lat": "12.952737709349638", "long": "77.53269953152314"}, {"lat": "12.951723008125086", "long": "77.52898847039434"}, {"lat": "12.955030621163779", "long": "77.53435792349025"}, {"lat": "12.945045479326126", "long": "77.56146638476822"}, {"lat": "12.944885419579766", "long": "77.56104829705465"}, {"lat": "12.947191136047943", "long": "77.54427035255277"}, {"lat": "12.92270001474177", "long": "77.63933052224958"}, {"lat": "12.92245915665578", "long": "77.63920351128718"}], "mapregion": [["12.906800439943844", "77.51125984192187"], ["13.04340042467224", "77.6809059887546"]]}
