{"galleryinfo": {"HID": 406, "HH": [1, 5], "HN": [1, 406], "HB": "Erythrina stricta var. suberosa, (Roxb.) Niyomdham", "HC": 36, "gallery": [{"IN": "Erythrina - Corky Coral Tree/Corky Coral Tree - Flower Bud.jpg", "IC": [1, 35]}, {"IN": "Erythrina - Corky Coral Tree/Corky Coral Tree - Flower.jpg", "IC": [1, 34]}, {"IN": "Erythrina - Corky Coral Tree/Corky Coral Tree - Fruit.jpg", "IC": [1, 59]}, {"IN": "Erythrina - Corky Coral Tree/Corky Coral Tree - Canopy.jpg", "IC": [1, 6]}, {"IN": "Erythrina - Corky Coral Tree/Corky Coral Tree - Leaf New.jpg", "IC": [1, 85]}, {"IN": "Erythrina - Corky Coral Tree/Corky Coral Tree - Leaf Tender.jpg", "IC": [1, 88]}, {"IN": "Erythrina - Corky Coral Tree/Corky Coral Tree - Leaf.jpg", "IC": [1, 76]}, {"IN": "Erythrina - Corky Coral Tree/Corky Coral Tree - Bark.jpg", "IC": [1, 1]}, {"IN": "Erythrina - Corky Coral Tree/Corky Coral Tree - Branch.jpg", "IC": [1, 4]}, {"IN": "Erythrina - Corky Coral Tree/Corky Coral Tree - 0000.jpg", "IC": [0, "0000"]}, {"IN": "Erythrina - Corky Coral Tree/Corky Coral Tree - 0001.jpg", "IC": [0, "0001"]}, {"IN": "Erythrina - Corky Coral Tree/Corky Coral Tree - 0002.jpg", "IC": [0, "0002"]}, {"IN": "Erythrina - Corky Coral Tree/Corky Coral Tree - 0003.jpg", "IC": [0, "0003"]}, {"IN": "Erythrina - Corky Coral Tree/Corky Coral Tree - 0004.jpg", "IC": [0, "0004"]}, {"IN": "Erythrina - Corky Coral Tree/Corky Coral Tree - 0005.jpg", "IC": [0, "0005"]}, {"IN": "Erythrina - Corky Coral Tree/Corky Coral Tree - 0006.jpg", "IC": [0, "0006"]}, {"IN": "Erythrina - Corky Coral Tree/Corky Coral Tree - 0007.jpg", "IC": [0, "0007"]}, {"IN": "Erythrina - Corky Coral Tree/Corky Coral Tree - 0008.jpg", "IC": [0, "0008"]}, {"IN": "Erythrina - Corky Coral Tree/Corky Coral Tree - 0009.jpg", "IC": [0, "0009"]}, {"IN": "Erythrina - Corky Coral Tree/Corky Coral Tree - 0010.jpg", "IC": [0, "0010"]}, {"IN": "Erythrina - Corky Coral Tree/Corky Coral Tree - 0011.jpg", "IC": [0, "0011"]}, {"IN": "Erythrina - Corky Coral Tree/Corky Coral Tree - 0012.jpg", "IC": [0, "0012"]}, {"IN": "Erythrina - Corky Coral Tree/Corky Coral Tree - 0013.jpg", "IC": [0, "0013"]}, {"IN": "Erythrina - Corky Coral Tree/Corky Coral Tree - 0014.jpg", "IC": [0, "0014"]}, {"IN": "Erythrina - Corky Coral Tree/Corky Coral Tree - 0015.jpg", "IC": [0, "0015"]}, {"IN": "Erythrina - Corky Coral Tree/Corky Coral Tree - 0016.jpg", "IC": [0, "0016"]}, {"IN": "Erythrina - Corky Coral Tree/Corky Coral Tree - 0017.jpg", "IC": [0, "0017"]}, {"IN": "Erythrina - Corky Coral Tree/Corky Coral Tree - 0018.jpg", "IC": [0, "0018"]}, {"IN": "Erythrina - Corky Coral Tree/Corky Coral Tree - 0019.jpg", "IC": [0, "0019"]}, {"IN": "Erythrina - Corky Coral Tree/Corky Coral Tree - 0020.jpg", "IC": [0, "0020"]}, {"IN": "Erythrina - Corky Coral Tree/Corky Coral Tree - 0021.jpg", "IC": [0, "0021"]}, {"IN": "Erythrina - Corky Coral Tree/Corky Coral Tree - 0022.jpg", "IC": [0, "0022"]}, {"IN": "Erythrina - Corky Coral Tree/Corky Coral Tree - 0023.jpg", "IC": [0, "0023"]}, {"IN": "Erythrina - Corky Coral Tree/Corky Coral Tree - 0024.jpg", "IC": [0, "0024"]}, {"IN": "Erythrina - Corky Coral Tree/Corky Coral Tree - 0025.jpg", "IC": [0, "0025"]}, {"IN": "Erythrina - Corky Coral Tree/Corky Coral Tree - 0026.jpg", "IC": [0, "0026"]}]}, "cardinfo": [{"CN": 6, "CV": [{"N": 19, "V": [1, 5, 406]}, {"N": 32, "V": [1, 3, 0]}, {"N": 7, "V": [0, "", "Fabaceae"]}, {"N": 30, "V": [0, "", "Faboideae"]}, {"N": 8, "V": [0, "", "Erythrina"]}, {"N": 26, "V": [0, "", "stricta var. suberosa"]}, {"N": 2, "V": [0, "", "(Roxb.) Niyomdham"]}, {"N": 4, "V": [0, "", "Pea"]}, {"N": 25, "V": [1, 2, 1]}, {"N": 9, "V": [1, 1, 3]}], "CI": "Erythrina - Corky Coral Tree/Corky Coral Tree - Canopy.jpg"}, {"CN": 9, "CV": [{"N": 17, "V": [0, "", "<a href=\"http://en.wikipedia.org/wiki/Erythrina_stricta\" target=\"_blank\">wikipedia</a><br /><a href=\"http://www.flowersofindia.net/catalog/slides/Corky%20Coral%20Tree.html\" target=\"_blank\">flowersofindia</a><br /><a href=\"http://www.ars-grin.gov/cgi-bin/npgs/html/taxon.pl?317849\" target=\"_blank\">ars-grin</a><br /><a href=\"http://www.theplantlist.org/tpl/record/ild-31145\" target=\"_blank\">theplantlist</a>"]}, {"N": 6, "V": [0, "", "Corky Coral Tree is a medium sized throny tree with distinctly orange, corky bark and an irregular crown. The tree is a captivating sight when in bloom, with clusters of bright, orange-scarlet up-facing flower clusters sitting at the end of branchlets like exotic waterlilies. Leaves are compound with three broad leaflets, the middle one the largest. Flowers have 5 petals of unequal length, and 10 stamens. Corky Coral Tree is native to the dry, mixed forests throughout India."]}, {"N": 20, "V": [0, "", ["India"]]}]}, {"CN": 0, "CV": [{"N": 3, "V": [1, 0, 2]}, {"N": 31, "V": [0, "", "Flaky"]}, {"N": 11, "V": [0, "", "Color: Pale Brown"]}], "CI": "Erythrina - Corky Coral Tree/Corky Coral Tree - Bark.jpg"}, {"CN": 3, "CV": [{"N": 3, "V": [1, 0, 6]}, {"N": 21, "V": [0, "", "Mar"]}, {"N": 11, "V": [0, "", "Color: orange scarlet"]}], "CI": "Erythrina - Corky Coral Tree/Corky Coral Tree - Flower.jpg"}, {"CN": 4, "CV": [{"N": 25, "V": [0, "", "20 cm"]}, {"N": 23, "V": [0, "", "Pod"]}], "CI": "Erythrina - Corky Coral Tree/Corky Coral Tree - Fruit.jpg"}, {"CN": 8, "CV": [{"N": 32, "V": [1, 4, 16]}, {"N": 24, "V": [0, "", "Mar-Apr"]}, {"N": 13, "V": [0, "", "3"]}], "CI": "Erythrina - Corky Coral Tree/Corky Coral Tree - Leaf.jpg"}], "mapinfo": [{"lat": "12.95320192", "long": "77.5840787"}], "mapregion": [["12.95320192", "77.5840787"], ["12.95320192", "77.5840787"]]}
